databrickslib/__init__.py
databrickslib/task.py
databrickslib-0.0.1.dist-info/METADATA
databrickslib-0.0.1.dist-info/WHEEL
databrickslib-0.0.1.dist-info/top_level.txt
databrickslib-0.0.1.dist-info/RECORD
